[
  {
    "text": "Google Skills for Partners",
    "href": "https://partner.skills.google/",
    "download": "",
    "internal": true
  },
  {
    "text": "Professional Cloud DevOps Engineer Certification",
    "href": "https://partner.skills.google/paths/20",
    "download": "",
    "internal": true
  },
  {
    "text": "Google Cloud",
    "href": "https://cloud.google.com/",
    "download": "",
    "internal": false
  },
  {
    "text": "Google Skills",
    "href": "https://www.skills.google/",
    "download": "",
    "internal": false
  },
  {
    "text": "Cloud console",
    "href": "https://cloud.google.com/cloud-console/",
    "download": "",
    "internal": false
  },
  {
    "text": "Get Started with Cloud Shell and gcloud",
    "href": "https://google.qwiklabs.com/catalog_lab/320",
    "download": "",
    "internal": false
  },
  {
    "text": "Create a Virtual Machine",
    "href": "https://google.qwiklabs.com/catalog_lab/1427",
    "download": "",
    "internal": false
  },
  {
    "text": "Google Cloud project",
    "href": "https://cloud.google.com/docs/overview/",
    "download": "",
    "internal": false
  },
  {
    "text": "Google Cloud products overview page",
    "href": "https://cloud.google.com/products/?hl=en",
    "download": "",
    "internal": false
  },
  {
    "text": "Cloud Identity and Access Management (Cloud IAM)",
    "href": "https://cloud.google.com/iam/",
    "download": "",
    "internal": false
  },
  {
    "text": "roles documentation",
    "href": "https://cloud.google.com/iam/docs/understanding-roles/",
    "download": "",
    "internal": false
  },
  {
    "text": "API Design Guide",
    "href": "https://cloud.google.com/apis/design/",
    "download": "",
    "internal": false
  },
  {
    "text": "Google APIs Explorer Directory",
    "href": "https://developers.google.com/apis-explorer/",
    "download": "",
    "internal": false
  },
  {
    "text": "APIs Explorer: Qwik Start",
    "href": "https://google.qwiklabs.com/catalog_lab/1241",
    "download": "",
    "internal": false
  },
  {
    "text": "Compute Engine: Qwik Start - Windows",
    "href": "https://google.qwiklabs.com/catalog_lab/759",
    "download": "",
    "internal": false
  },
  {
    "text": "Our classes",
    "href": "https://cloud.google.com/training",
    "download": "",
    "internal": false
  },
  {
    "text": "Certifications",
    "href": "https://cloud.google.com/certification/",
    "download": "",
    "internal": false
  },
  {
    "text": "",
    "href": "https://partner.skills.google/focuses/71328?parent=catalog",
    "download": "",
    "internal": true
  },
  {
    "text": "Dashboard",
    "href": "https://partner.skills.google/",
    "download": "",
    "internal": true
  },
  {
    "text": "Catalog",
    "href": "https://partner.skills.google/catalog",
    "download": "",
    "internal": true
  },
  {
    "text": "Paths",
    "href": "https://partner.skills.google/paths",
    "download": "",
    "internal": true
  },
  {
    "text": "Subscriptions",
    "href": "https://partner.skills.google/subscriptions",
    "download": "",
    "internal": true
  },
  {
    "text": "Activities",
    "href": "https://partner.skills.google/profile/stay_on_track",
    "download": "",
    "internal": true
  },
  {
    "text": "Achievements",
    "href": "https://partner.skills.google/profile/badges",
    "download": "",
    "internal": true
  },
  {
    "text": "Settings",
    "href": "https://partner.skills.google/my_account/profile",
    "download": "",
    "internal": true
  },
  {
    "text": "Sign out",
    "href": "https://partner.skills.google/users/sign_out",
    "download": "",
    "internal": true
  },
  {
    "text": "Youtube",
    "href": "https://www.youtube.com/@googlecloud",
    "download": "",
    "internal": false
  },
  {
    "text": "Help Center",
    "href": "https://partner.skills.google/help",
    "download": "",
    "internal": true
  },
  {
    "text": "Terms",
    "href": "https://partner.skills.google/terms_of_service",
    "download": "",
    "internal": true
  },
  {
    "text": "Privacy",
    "href": "https://partner.skills.google/privacy_policy",
    "download": "",
    "internal": true
  },
  {
    "text": "https://partner.skills.google/catalog_lab/1281",
    "href": "https://partner.skills.google/catalog_lab/1281",
    "download": "",
    "internal": true
  },
  {
    "text": "Jump to content",
    "href": "https://partner.skills.google/focuses/11600?parent=catalog&path=20",
    "download": "",
    "internal": true
  },
  {
    "text": "Share on LinkedIn Feed",
    "href": "https://www.linkedin.com/sharing/share-offsite/?url=https%3A%2F%2Fpartner.skills.google%2Fcatalog_lab%2F1281%3Futm_medium%3Dsocial%26utm_source%3Dlinkedin%26utm_campaign%3Dql-social-share",
    "download": "",
    "internal": false
  },
  {
    "text": "X",
    "href": "https://x.com/intent/tweet?text=Learn+cloud+tech+through+hands-on+training+on+%23GoogleSkills%21&url=https%3A%2F%2Fpartner.skills.google%2Fcatalog_lab%2F1281%3Futm_medium%3Dsocial%26utm_source%3Dx%26utm_campaign%3Dql-social-share&hashtags=",
    "download": "",
    "internal": false
  },
  {
    "text": "Facebook",
    "href": "https://facebook.com/sharer.php?display=popup&u=https%3A%2F%2Fpartner.skills.google%2Fcatalog_lab%2F1281%3Futm_medium%3Dsocial%26utm_source%3Dfacebook%26utm_campaign%3Dql-social-share",
    "download": "",
    "internal": false
  },
  {
    "text": "Contact Us",
    "href": "https://support.google.com/qwiklabs/contact/Google_Skills_Partner",
    "download": "",
    "internal": false
  },
  {
    "text": "Report Illegal Content",
    "href": "https://reportingwidget.google.com/widget/54?cid=1&url=https%3A%2F%2Fpartner.skills.google%2Ffocuses%2F11600%3F",
    "download": "",
    "internal": false
  },
  {
    "text": "العربية‬‎",
    "href": "https://partner.skills.google/focuses/11600?locale=ar&parent=catalog&path=20",
    "download": "",
    "internal": true
  },
  {
    "text": "Deutsch",
    "href": "https://partner.skills.google/focuses/11600?locale=de&parent=catalog&path=20",
    "download": "",
    "internal": true
  },
  {
    "text": "English",
    "href": "https://partner.skills.google/focuses/11600?locale=en&parent=catalog&path=20",
    "download": "",
    "internal": true
  },
  {
    "text": "español (Latinoamérica)",
    "href": "https://partner.skills.google/focuses/11600?locale=es&parent=catalog&path=20",
    "download": "",
    "internal": true
  },
  {
    "text": "français",
    "href": "https://partner.skills.google/focuses/11600?locale=fr&parent=catalog&path=20",
    "download": "",
    "internal": true
  },
  {
    "text": "français (Canada)",
    "href": "https://partner.skills.google/focuses/11600?locale=fr_CA&parent=catalog&path=20",
    "download": "",
    "internal": true
  },
  {
    "text": "עברית",
    "href": "https://partner.skills.google/focuses/11600?locale=he&parent=catalog&path=20",
    "download": "",
    "internal": true
  },
  {
    "text": "bahasa Indonesia",
    "href": "https://partner.skills.google/focuses/11600?locale=id&parent=catalog&path=20",
    "download": "",
    "internal": true
  },
  {
    "text": "italiano",
    "href": "https://partner.skills.google/focuses/11600?locale=it&parent=catalog&path=20",
    "download": "",
    "internal": true
  },
  {
    "text": "日本語",
    "href": "https://partner.skills.google/focuses/11600?locale=ja&parent=catalog&path=20",
    "download": "",
    "internal": true
  },
  {
    "text": "한국어",
    "href": "https://partner.skills.google/focuses/11600?locale=ko&parent=catalog&path=20",
    "download": "",
    "internal": true
  },
  {
    "text": "polski",
    "href": "https://partner.skills.google/focuses/11600?locale=pl&parent=catalog&path=20",
    "download": "",
    "internal": true
  },
  {
    "text": "português (Brasil)",
    "href": "https://partner.skills.google/focuses/11600?locale=pt_BR&parent=catalog&path=20",
    "download": "",
    "internal": true
  },
  {
    "text": "português (Portugal)",
    "href": "https://partner.skills.google/focuses/11600?locale=pt_PT&parent=catalog&path=20",
    "download": "",
    "internal": true
  },
  {
    "text": "русский",
    "href": "https://partner.skills.google/focuses/11600?locale=ru&parent=catalog&path=20",
    "download": "",
    "internal": true
  },
  {
    "text": "Türkçe",
    "href": "https://partner.skills.google/focuses/11600?locale=tr&parent=catalog&path=20",
    "download": "",
    "internal": true
  },
  {
    "text": "українська",
    "href": "https://partner.skills.google/focuses/11600?locale=uk&parent=catalog&path=20",
    "download": "",
    "internal": true
  },
  {
    "text": "简体中文",
    "href": "https://partner.skills.google/focuses/11600?locale=zh&parent=catalog&path=20",
    "download": "",
    "internal": true
  },
  {
    "text": "繁體中文",
    "href": "https://partner.skills.google/focuses/11600?locale=zh_TW&parent=catalog&path=20",
    "download": "",
    "internal": true
  },
  {
    "text": "Progress",
    "href": "https://partner.skills.google/profile/activity",
    "download": "",
    "internal": true
  },
  {
    "text": "Programs",
    "href": "https://partner.skills.google/my_account/programs",
    "download": "",
    "internal": true
  },
  {
    "text": "home_filled",
    "href": "https://partner.skills.google/",
    "download": "",
    "internal": true
  },
  {
    "text": "No, thanks",
    "href": "https://partner.skills.google/focuses/11600/set_up_lab_forward_url?parent=catalog&path=20",
    "download": "",
    "internal": true
  },
  {
    "text": "Back to screen",
    "href": "https://partner.skills.google/focuses/11600/set_up_lab_forward_url?parent=catalog&path=20",
    "download": "",
    "internal": true
  }
]